pandasHana/__init__.py
pandasHana/pandasHana.py
pandasHana-0.0.1.dist-info/LICENSE
pandasHana-0.0.1.dist-info/METADATA
pandasHana-0.0.1.dist-info/WHEEL
pandasHana-0.0.1.dist-info/top_level.txt
pandasHana-0.0.1.dist-info/RECORD
